mplpanel/__init__.py
mplpanel/graph.py
mplpanel/graph_backend.py
mplpanel/graph_canvas.py
mplpanel/graph_common.py
mplpanel/graph_datatip.py
mplpanel/graph_dock.py
mplpanel/graph_edit.py
mplpanel/graph_stats.py
mplpanel/graph_subplot.py
mplpanel/graph_svg.py
mplpanel/graph_timeline.py
mplpanel/graph_toolbar.py
mplpanel/utility.py
mplpanel/version.py
mplpanel-0.2.4.dist-info/METADATA
mplpanel-0.2.4.dist-info/WHEEL
mplpanel-0.2.4.dist-info/top_level.txt
mplpanel-0.2.4.dist-info/RECORD
