Metadata-Version: 2.2
Name: mplpanel
Version: 0.2.4
Summary: A wx.Panel to use matplotlib plot in wxPython
Author-email: Tianzhu Qiao <tq@feiyilin.com>
Project-URL: Homepage, https://github.com/tianzhuqiao/mplpanel
Classifier: Operating System :: OS Independent
Requires-Python: >=3.0
Requires-Dist: wxpython>=4.2.1
Requires-Dist: matplotlib>=3.8.1
Requires-Dist: packaging
Requires-Dist: numpy
Requires-Dist: pandas
Requires-Dist: pillow
Requires-Dist: aui2>=0.1.9
Requires-Dist: propgrid>=0.1.6
